aiodownloads/__init__.py
aiodownloads/downloader.py
aiodownloads-0.2.0.dist-info/LICENSE
aiodownloads-0.2.0.dist-info/WHEEL
aiodownloads-0.2.0.dist-info/METADATA
aiodownloads-0.2.0.dist-info/RECORD
