Metadata-Version: 2.1
Name: aiodownloads
Version: 0.2.0
Summary: Asynchronous downloads
Home-page: https://github.com/tinnguyentg/aiodownloads
License: MIT
Author: tinnguyen121221
Author-email: tinnguyen121221@gmail.com
Requires-Python: >=3.9,<4.0
Classifier: License :: OSI Approved :: MIT License
Classifier: Programming Language :: Python :: 3
Classifier: Programming Language :: Python :: 3.10
Classifier: Programming Language :: Python :: 3.9
Requires-Dist: aiohttp (>=3.8.1,<4.0.0)
Project-URL: Repository, https://github.com/tinnguyentg/aiodownloads
